{
  "fio version" : "fio-3.27",
  "timestamp" : 1627434016,
  "timestamp_ms" : 1627434016554,
  "time" : "Wed Jul 28 03:00:16 2021",
  "jobs" : [
    {
      "jobname" : "seq-read",
      "groupid" : 0,
      "error" : 0,
      "eta" : 0,
      "elapsed" : 301,
      "job options" : {
        "bs" : "4K",
        "iodepth" : "256",
        "direct" : "1",
        "ioengine" : "libaio",
        "time_based" : "1",
        "runtime" : "300",
        "numjobs" : "4",
        "size" : "1g",
        "name" : "seq-read",
        "rw" : "read",
        "directory" : "/scratch/snx2000/ccocha/seqread/128_node/",
        "filename_format" : "$jobname.3.$jobnum.$filenum"
      },
      "read" : {
        "io_bytes" : 5409918976,
        "io_kbytes" : 5283124,
        "bw_bytes" : 18032161,
        "bw" : 17609,
        "iops" : 4402.383214,
        "runtime" : 300015,
        "total_ios" : 1320781,
        "short_ios" : 0,
        "drop_ios" : 0,
        "slat_ns" : {
          "min" : 398797,
          "max" : 116778756,
          "mean" : 892775.335507,
          "stddev" : 1043025.988119,
          "N" : 1320781
        },
        "clat_ns" : {
          "min" : 11270,
          "max" : 521698372,
          "mean" : 231557289.776787,
          "stddev" : 27163528.466674,
          "N" : 1320781,
          "percentile" : {
            "1.000000" : 193986560,
            "5.000000" : 200278016,
            "10.000000" : 204472320,
            "20.000000" : 210763776,
            "30.000000" : 214958080,
            "40.000000" : 221249536,
            "50.000000" : 225443840,
            "60.000000" : 231735296,
            "70.000000" : 238026752,
            "80.000000" : 248512512,
            "90.000000" : 267386880,
            "95.000000" : 283115520,
            "99.000000" : 320864256,
            "99.500000" : 337641472,
            "99.900000" : 375390208,
            "99.950000" : 392167424,
            "99.990000" : 467664896
          }
        },
        "lat_ns" : {
          "min" : 540099,
          "max" : 522562306,
          "mean" : 232451971.953754,
          "stddev" : 27228985.337655,
          "N" : 1320781
        },
        "bw_min" : 6248,
        "bw_max" : 20704,
        "bw_agg" : 99.979941,
        "bw_mean" : 17606.103506,
        "bw_dev" : 382.954387,
        "bw_samples" : 2396,
        "iops_min" : 1562,
        "iops_max" : 5176,
        "iops_mean" : 4401.532554,
        "iops_stddev" : 95.743224,
        "iops_samples" : 2396
      },
      "write" : {
        "io_bytes" : 0,
        "io_kbytes" : 0,
        "bw_bytes" : 0,
        "bw" : 0,
        "iops" : 0.000000,
        "runtime" : 0,
        "total_ios" : 0,
        "short_ios" : 0,
        "drop_ios" : 0,
        "slat_ns" : {
          "min" : 0,
          "max" : 0,
          "mean" : 0.000000,
          "stddev" : 0.000000,
          "N" : 0
        },
        "clat_ns" : {
          "min" : 0,
          "max" : 0,
          "mean" : 0.000000,
          "stddev" : 0.000000,
          "N" : 0
        },
        "lat_ns" : {
          "min" : 0,
          "max" : 0,
          "mean" : 0.000000,
          "stddev" : 0.000000,
          "N" : 0
        },
        "bw_min" : 0,
        "bw_max" : 0,
        "bw_agg" : 0.000000,
        "bw_mean" : 0.000000,
        "bw_dev" : 0.000000,
        "bw_samples" : 0,
        "iops_min" : 0,
        "iops_max" : 0,
        "iops_mean" : 0.000000,
        "iops_stddev" : 0.000000,
        "iops_samples" : 0
      },
      "trim" : {
        "io_bytes" : 0,
        "io_kbytes" : 0,
        "bw_bytes" : 0,
        "bw" : 0,
        "iops" : 0.000000,
        "runtime" : 0,
        "total_ios" : 0,
        "short_ios" : 0,
        "drop_ios" : 0,
        "slat_ns" : {
          "min" : 0,
          "max" : 0,
          "mean" : 0.000000,
          "stddev" : 0.000000,
          "N" : 0
        },
        "clat_ns" : {
          "min" : 0,
          "max" : 0,
          "mean" : 0.000000,
          "stddev" : 0.000000,
          "N" : 0
        },
        "lat_ns" : {
          "min" : 0,
          "max" : 0,
          "mean" : 0.000000,
          "stddev" : 0.000000,
          "N" : 0
        },
        "bw_min" : 0,
        "bw_max" : 0,
        "bw_agg" : 0.000000,
        "bw_mean" : 0.000000,
        "bw_dev" : 0.000000,
        "bw_samples" : 0,
        "iops_min" : 0,
        "iops_max" : 0,
        "iops_mean" : 0.000000,
        "iops_stddev" : 0.000000,
        "iops_samples" : 0
      },
      "sync" : {
        "total_ios" : 0,
        "lat_ns" : {
          "min" : 0,
          "max" : 0,
          "mean" : 0.000000,
          "stddev" : 0.000000,
          "N" : 0
        }
      },
      "job_runtime" : 1200014,
      "usr_cpu" : 2.004060,
      "sys_cpu" : 13.149680,
      "ctx" : 1320929,
      "majf" : 0,
      "minf" : 1183,
      "iodepth_level" : {
        "1" : 0.100000,
        "2" : 0.100000,
        "4" : 0.100000,
        "8" : 0.100000,
        "16" : 0.100000,
        "32" : 0.100000,
        ">=64" : 99.980920
      },
      "iodepth_submit" : {
        "0" : 0.000000,
        "4" : 100.000000,
        "8" : 0.000000,
        "16" : 0.000000,
        "32" : 0.000000,
        "64" : 0.000000,
        ">=64" : 0.000000
      },
      "iodepth_complete" : {
        "0" : 0.000000,
        "4" : 99.999697,
        "8" : 0.000000,
        "16" : 0.000000,
        "32" : 0.000000,
        "64" : 0.000000,
        ">=64" : 0.100000
      },
      "latency_ns" : {
        "2" : 0.000000,
        "4" : 0.000000,
        "10" : 0.000000,
        "20" : 0.000000,
        "50" : 0.000000,
        "100" : 0.000000,
        "250" : 0.000000,
        "500" : 0.000000,
        "750" : 0.000000,
        "1000" : 0.000000
      },
      "latency_us" : {
        "2" : 0.000000,
        "4" : 0.000000,
        "10" : 0.000000,
        "20" : 0.010000,
        "50" : 0.000000,
        "100" : 0.000000,
        "250" : 0.000000,
        "500" : 0.000000,
        "750" : 0.010000,
        "1000" : 0.000000
      },
      "latency_ms" : {
        "2" : 0.010000,
        "4" : 0.010000,
        "10" : 0.010000,
        "20" : 0.010000,
        "50" : 0.012493,
        "100" : 0.020518,
        "250" : 80.659171,
        "500" : 19.298430,
        "750" : 0.010000,
        "1000" : 0.000000,
        "2000" : 0.000000,
        ">=2000" : 0.000000
      },
      "latency_depth" : 256,
      "latency_target" : 0,
      "latency_percentile" : 100.000000,
      "latency_window" : 0
    }
  ]
}
