{
  "fio version" : "fio-3.27",
  "timestamp" : 1627025125,
  "timestamp_ms" : 1627025125944,
  "time" : "Fri Jul 23 09:25:25 2021",
  "jobs" : [
    {
      "jobname" : "randrw",
      "groupid" : 0,
      "error" : 0,
      "eta" : 0,
      "elapsed" : 301,
      "job options" : {
        "bs" : "4K",
        "iodepth" : "256",
        "direct" : "0",
        "ioengine" : "libaio",
        "time_based" : "1",
        "runtime" : "300",
        "numjobs" : "1",
        "size" : "1g",
        "name" : "randrw",
        "rw" : "randrw",
        "directory" : "/scratch/snx2000/ccocha/randrw/128_node",
        "filename_format" : "$jobname.125.$jobnum.$filenum"
      },
      "read" : {
        "io_bytes" : 81199104,
        "io_kbytes" : 79296,
        "bw_bytes" : 270651,
        "bw" : 264,
        "iops" : 66.077137,
        "runtime" : 300013,
        "total_ios" : 19824,
        "short_ios" : 0,
        "drop_ios" : 0,
        "slat_ns" : {
          "min" : 465234,
          "max" : 981260803,
          "mean" : 14995452.927966,
          "stddev" : 36164010.690717,
          "N" : 19824
        },
        "clat_ns" : {
          "min" : 12770,
          "max" : 13037052641,
          "mean" : 1926977251.043496,
          "stddev" : 1270961019.833609,
          "N" : 19824,
          "percentile" : {
            "1.000000" : 650117120,
            "5.000000" : 708837376,
            "10.000000" : 759169024,
            "20.000000" : 985661440,
            "30.000000" : 1266679808,
            "40.000000" : 1535115264,
            "50.000000" : 1769996288,
            "60.000000" : 1988100096,
            "70.000000" : 2264924160,
            "80.000000" : 2533359616,
            "90.000000" : 2969567232,
            "95.000000" : 3472883712,
            "99.000000" : 6677331968,
            "99.500000" : 11878268928,
            "99.900000" : 12952010752,
            "99.950000" : 12952010752,
            "99.990000" : 13086228480
          }
        },
        "lat_ns" : {
          "min" : 15455516,
          "max" : 13044514657,
          "mean" : 1941975306.431095,
          "stddev" : 1275457876.733459,
          "N" : 19824
        },
        "bw_min" : 8,
        "bw_max" : 840,
        "bw_agg" : 100.000000,
        "bw_mean" : 270.039451,
        "bw_dev" : 190.394021,
        "bw_samples" : 583,
        "iops_min" : 2,
        "iops_max" : 210,
        "iops_mean" : 67.506003,
        "iops_stddev" : 47.591361,
        "iops_samples" : 583
      },
      "write" : {
        "io_bytes" : 81330176,
        "io_kbytes" : 79424,
        "bw_bytes" : 271088,
        "bw" : 264,
        "iops" : 66.183799,
        "runtime" : 300013,
        "total_ios" : 19856,
        "short_ios" : 0,
        "drop_ios" : 0,
        "slat_ns" : {
          "min" : 75220,
          "max" : 528924,
          "mean" : 105498.475322,
          "stddev" : 41061.561458,
          "N" : 19856
        },
        "clat_ns" : {
          "min" : 15465146,
          "max" : 13041610885,
          "mean" : 1924904762.747933,
          "stddev" : 1247491066.977281,
          "N" : 19856,
          "percentile" : {
            "1.000000" : 641728512,
            "5.000000" : 708837376,
            "10.000000" : 759169024,
            "20.000000" : 985661440,
            "30.000000" : 1249902592,
            "40.000000" : 1518338048,
            "50.000000" : 1769996288,
            "60.000000" : 1988100096,
            "70.000000" : 2264924160,
            "80.000000" : 2533359616,
            "90.000000" : 2969567232,
            "95.000000" : 3472883712,
            "99.000000" : 6677331968,
            "99.500000" : 9059696640,
            "99.900000" : 12952010752,
            "99.950000" : 12952010752,
            "99.990000" : 13086228480
          }
        },
        "lat_ns" : {
          "min" : 15554927,
          "max" : 13041799336,
          "mean" : 1925011399.602384,
          "stddev" : 1247492146.818733,
          "N" : 19856
        },
        "bw_min" : 8,
        "bw_max" : 881,
        "bw_agg" : 100.000000,
        "bw_mean" : 272.823529,
        "bw_dev" : 194.456644,
        "bw_samples" : 578,
        "iops_min" : 2,
        "iops_max" : 220,
        "iops_mean" : 68.200692,
        "iops_stddev" : 48.605381,
        "iops_samples" : 578
      },
      "trim" : {
        "io_bytes" : 0,
        "io_kbytes" : 0,
        "bw_bytes" : 0,
        "bw" : 0,
        "iops" : 0.000000,
        "runtime" : 0,
        "total_ios" : 0,
        "short_ios" : 0,
        "drop_ios" : 0,
        "slat_ns" : {
          "min" : 0,
          "max" : 0,
          "mean" : 0.000000,
          "stddev" : 0.000000,
          "N" : 0
        },
        "clat_ns" : {
          "min" : 0,
          "max" : 0,
          "mean" : 0.000000,
          "stddev" : 0.000000,
          "N" : 0
        },
        "lat_ns" : {
          "min" : 0,
          "max" : 0,
          "mean" : 0.000000,
          "stddev" : 0.000000,
          "N" : 0
        },
        "bw_min" : 0,
        "bw_max" : 0,
        "bw_agg" : 0.000000,
        "bw_mean" : 0.000000,
        "bw_dev" : 0.000000,
        "bw_samples" : 0,
        "iops_min" : 0,
        "iops_max" : 0,
        "iops_mean" : 0.000000,
        "iops_stddev" : 0.000000,
        "iops_samples" : 0
      },
      "sync" : {
        "total_ios" : 0,
        "lat_ns" : {
          "min" : 0,
          "max" : 0,
          "mean" : 0.000000,
          "stddev" : 0.000000,
          "N" : 0
        }
      },
      "job_runtime" : 300012,
      "usr_cpu" : 0.248657,
      "sys_cpu" : 1.661267,
      "ctx" : 19834,
      "majf" : 0,
      "minf" : 43,
      "iodepth_level" : {
        "1" : 0.100000,
        "2" : 0.100000,
        "4" : 0.100000,
        "8" : 0.100000,
        "16" : 0.100000,
        "32" : 0.100000,
        ">=64" : 99.841230
      },
      "iodepth_submit" : {
        "0" : 0.000000,
        "4" : 100.000000,
        "8" : 0.000000,
        "16" : 0.000000,
        "32" : 0.000000,
        "64" : 0.000000,
        ">=64" : 0.000000
      },
      "iodepth_complete" : {
        "0" : 0.000000,
        "4" : 99.997464,
        "8" : 0.000000,
        "16" : 0.000000,
        "32" : 0.000000,
        "64" : 0.000000,
        ">=64" : 0.100000
      },
      "latency_ns" : {
        "2" : 0.000000,
        "4" : 0.000000,
        "10" : 0.000000,
        "20" : 0.000000,
        "50" : 0.000000,
        "100" : 0.000000,
        "250" : 0.000000,
        "500" : 0.000000,
        "750" : 0.000000,
        "1000" : 0.000000
      },
      "latency_us" : {
        "2" : 0.000000,
        "4" : 0.000000,
        "10" : 0.000000,
        "20" : 0.010000,
        "50" : 0.000000,
        "100" : 0.000000,
        "250" : 0.000000,
        "500" : 0.000000,
        "750" : 0.000000,
        "1000" : 0.000000
      },
      "latency_ms" : {
        "2" : 0.000000,
        "4" : 0.000000,
        "10" : 0.000000,
        "20" : 0.012601,
        "50" : 0.017641,
        "100" : 0.010000,
        "250" : 0.017641,
        "500" : 0.060484,
        "750" : 8.986895,
        "1000" : 11.489415,
        "2000" : 40.012601,
        ">=2000" : 39.397681
      },
      "latency_depth" : 256,
      "latency_target" : 0,
      "latency_percentile" : 100.000000,
      "latency_window" : 0
    }
  ]
}
