{
  "fio version" : "fio-3.27",
  "timestamp" : 1627031994,
  "timestamp_ms" : 1627031994125,
  "time" : "Fri Jul 23 11:19:54 2021",
  "jobs" : [
    {
      "jobname" : "randrw",
      "groupid" : 0,
      "error" : 0,
      "eta" : 0,
      "elapsed" : 302,
      "job options" : {
        "bs" : "4K",
        "iodepth" : "256",
        "direct" : "0",
        "ioengine" : "libaio",
        "time_based" : "1",
        "runtime" : "300",
        "numjobs" : "64",
        "size" : "1g",
        "name" : "randrw",
        "rw" : "randrw",
        "directory" : "/scratch/snx2000/ccocha/randrw/150_node",
        "filename_format" : "$jobname.0.$jobnum.$filenum"
      },
      "read" : {
        "io_bytes" : 49557504,
        "io_kbytes" : 48396,
        "bw_bytes" : 164715,
        "bw" : 160,
        "iops" : 40.213649,
        "runtime" : 300868,
        "total_ios" : 12099,
        "short_ios" : 0,
        "drop_ios" : 0,
        "slat_ns" : {
          "min" : 96816220,
          "max" : 86189914828,
          "mean" : 1589448549.989173,
          "stddev" : 4728637978.730780,
          "N" : 12099
        },
        "clat_ns" : {
          "min" : 19671,
          "max" : 299480135496,
          "mean" : 154213906491.419830,
          "stddev" : 84655967822.051315,
          "N" : 12099,
          "percentile" : {
            "1.000000" : 2164260864,
            "5.000000" : 16039018496,
            "10.000000" : 17112760320,
            "20.000000" : 17112760320,
            "30.000000" : 17112760320,
            "40.000000" : 17112760320,
            "50.000000" : 17112760320,
            "60.000000" : 17112760320,
            "70.000000" : 17112760320,
            "80.000000" : 17112760320,
            "90.000000" : 17112760320,
            "95.000000" : 17112760320,
            "99.000000" : 17112760320,
            "99.500000" : 17112760320,
            "99.900000" : 17112760320,
            "99.950000" : 17112760320,
            "99.990000" : 17112760320
          }
        },
        "lat_ns" : {
          "min" : 611178152,
          "max" : 299629007453,
          "mean" : 155803359395.500732,
          "stddev" : 84477584972.499084,
          "N" : 12099
        },
        "bw_min" : 520,
        "bw_max" : 2112,
        "bw_agg" : 100.000000,
        "bw_mean" : 774.465337,
        "bw_dev" : 6.693477,
        "bw_samples" : 2553,
        "iops_min" : 130,
        "iops_max" : 528,
        "iops_mean" : 193.616334,
        "iops_stddev" : 1.673369,
        "iops_samples" : 2553
      },
      "write" : {
        "io_bytes" : 49033216,
        "io_kbytes" : 47884,
        "bw_bytes" : 162972,
        "bw" : 159,
        "iops" : 39.788213,
        "runtime" : 300868,
        "total_ios" : 11971,
        "short_ios" : 0,
        "drop_ios" : 0,
        "slat_ns" : {
          "min" : 75562,
          "max" : 3525250,
          "mean" : 142114.165650,
          "stddev" : 114428.201476,
          "N" : 11971
        },
        "clat_ns" : {
          "min" : 611188742,
          "max" : 299479952374,
          "mean" : 155137022415.499908,
          "stddev" : 84530975007.048965,
          "N" : 11971,
          "percentile" : {
            "1.000000" : 3976200192,
            "5.000000" : 17112760320,
            "10.000000" : 17112760320,
            "20.000000" : 17112760320,
            "30.000000" : 17112760320,
            "40.000000" : 17112760320,
            "50.000000" : 17112760320,
            "60.000000" : 17112760320,
            "70.000000" : 17112760320,
            "80.000000" : 17112760320,
            "90.000000" : 17112760320,
            "95.000000" : 17112760320,
            "99.000000" : 17112760320,
            "99.500000" : 17112760320,
            "99.900000" : 17112760320,
            "99.950000" : 17112760320,
            "99.990000" : 17112760320
          }
        },
        "lat_ns" : {
          "min" : 611291324,
          "max" : 299480134067,
          "mean" : 155137165912.076752,
          "stddev" : 84530972285.924667,
          "N" : 11971
        },
        "bw_min" : 512,
        "bw_max" : 2256,
        "bw_agg" : 100.000000,
        "bw_mean" : 760.594185,
        "bw_dev" : 7.096049,
        "bw_samples" : 2566,
        "iops_min" : 128,
        "iops_max" : 564,
        "iops_mean" : 190.148546,
        "iops_stddev" : 1.774012,
        "iops_samples" : 2566
      },
      "trim" : {
        "io_bytes" : 0,
        "io_kbytes" : 0,
        "bw_bytes" : 0,
        "bw" : 0,
        "iops" : 0.000000,
        "runtime" : 0,
        "total_ios" : 0,
        "short_ios" : 0,
        "drop_ios" : 0,
        "slat_ns" : {
          "min" : 0,
          "max" : 0,
          "mean" : 0.000000,
          "stddev" : 0.000000,
          "N" : 0
        },
        "clat_ns" : {
          "min" : 0,
          "max" : 0,
          "mean" : 0.000000,
          "stddev" : 0.000000,
          "N" : 0
        },
        "lat_ns" : {
          "min" : 0,
          "max" : 0,
          "mean" : 0.000000,
          "stddev" : 0.000000,
          "N" : 0
        },
        "bw_min" : 0,
        "bw_max" : 0,
        "bw_agg" : 0.000000,
        "bw_mean" : 0.000000,
        "bw_dev" : 0.000000,
        "bw_samples" : 0,
        "iops_min" : 0,
        "iops_max" : 0,
        "iops_mean" : 0.000000,
        "iops_stddev" : 0.000000,
        "iops_samples" : 0
      },
      "sync" : {
        "total_ios" : 0,
        "lat_ns" : {
          "min" : 0,
          "max" : 0,
          "mean" : 0.000000,
          "stddev" : 0.000000,
          "N" : 0
        }
      },
      "job_runtime" : 19233279,
      "usr_cpu" : 0.002678,
      "sys_cpu" : 0.021130,
      "ctx" : 12790,
      "majf" : 0,
      "minf" : 2606,
      "iodepth_level" : {
        "1" : 0.265891,
        "2" : 0.531782,
        "4" : 1.063565,
        "8" : 2.127129,
        "16" : 4.254258,
        "32" : 8.508517,
        ">=64" : 83.248857
      },
      "iodepth_submit" : {
        "0" : 0.000000,
        "4" : 100.000000,
        "8" : 0.000000,
        "16" : 0.000000,
        "32" : 0.000000,
        "64" : 0.000000,
        ">=64" : 0.000000
      },
      "iodepth_complete" : {
        "0" : 0.000000,
        "4" : 99.180957,
        "8" : 0.000000,
        "16" : 0.000000,
        "32" : 0.000000,
        "64" : 0.000000,
        ">=64" : 0.819043
      },
      "latency_ns" : {
        "2" : 0.000000,
        "4" : 0.000000,
        "10" : 0.000000,
        "20" : 0.000000,
        "50" : 0.000000,
        "100" : 0.000000,
        "250" : 0.000000,
        "500" : 0.000000,
        "750" : 0.000000,
        "1000" : 0.000000
      },
      "latency_us" : {
        "2" : 0.000000,
        "4" : 0.000000,
        "10" : 0.000000,
        "20" : 0.010000,
        "50" : 0.261737,
        "100" : 0.000000,
        "250" : 0.000000,
        "500" : 0.000000,
        "750" : 0.000000,
        "1000" : 0.000000
      },
      "latency_ms" : {
        "2" : 0.000000,
        "4" : 0.000000,
        "10" : 0.000000,
        "20" : 0.000000,
        "50" : 0.000000,
        "100" : 0.000000,
        "250" : 0.000000,
        "500" : 0.000000,
        "750" : 0.062318,
        "1000" : 0.112173,
        "2000" : 0.324055,
        ">=2000" : 99.235563
      },
      "latency_depth" : 256,
      "latency_target" : 0,
      "latency_percentile" : 100.000000,
      "latency_window" : 0
    }
  ]
}
