{
  "fio version" : "fio-3.27",
  "timestamp" : 1627030354,
  "timestamp_ms" : 1627030354423,
  "time" : "Fri Jul 23 10:52:34 2021",
  "jobs" : [
    {
      "jobname" : "randrw",
      "groupid" : 0,
      "error" : 0,
      "eta" : 0,
      "elapsed" : 302,
      "job options" : {
        "bs" : "4K",
        "iodepth" : "256",
        "direct" : "0",
        "ioengine" : "libaio",
        "time_based" : "1",
        "runtime" : "300",
        "numjobs" : "16",
        "size" : "1g",
        "name" : "randrw",
        "rw" : "randrw",
        "directory" : "/scratch/snx2000/ccocha/randrw/150_node",
        "filename_format" : "$jobname.74.$jobnum.$filenum"
      },
      "read" : {
        "io_bytes" : 81907712,
        "io_kbytes" : 79988,
        "bw_bytes" : 271685,
        "bw" : 265,
        "iops" : 66.329441,
        "runtime" : 301480,
        "total_ios" : 19997,
        "short_ios" : 0,
        "drop_ios" : 0,
        "slat_ns" : {
          "min" : 557316,
          "max" : 88370973619,
          "mean" : 240261315.977147,
          "stddev" : 2164832560.786218,
          "N" : 19997
        },
        "clat_ns" : {
          "min" : 20621,
          "max" : 129648211031,
          "mean" : 30391571696.554684,
          "stddev" : 29942532314.170921,
          "N" : 19997,
          "percentile" : {
            "1.000000" : 2466250752,
            "5.000000" : 3103784960,
            "10.000000" : 3338665984,
            "20.000000" : 3607101440,
            "30.000000" : 4110417920,
            "40.000000" : 17112760320,
            "50.000000" : 17112760320,
            "60.000000" : 17112760320,
            "70.000000" : 17112760320,
            "80.000000" : 17112760320,
            "90.000000" : 17112760320,
            "95.000000" : 17112760320,
            "99.000000" : 17112760320,
            "99.500000" : 17112760320,
            "99.900000" : 17112760320,
            "99.950000" : 17112760320,
            "99.990000" : 17112760320
          }
        },
        "lat_ns" : {
          "min" : 836671015,
          "max" : 129684054764,
          "mean" : 30631836432.100266,
          "stddev" : 30068427199.585522,
          "N" : 19997
        },
        "bw_min" : 128,
        "bw_max" : 3504,
        "bw_agg" : 100.000000,
        "bw_mean" : 607.322235,
        "bw_dev" : 41.640839,
        "bw_samples" : 3771,
        "iops_min" : 32,
        "iops_max" : 876,
        "iops_mean" : 151.830559,
        "iops_stddev" : 10.410210,
        "iops_samples" : 3771
      },
      "write" : {
        "io_bytes" : 82235392,
        "io_kbytes" : 80308,
        "bw_bytes" : 272772,
        "bw" : 266,
        "iops" : 66.594799,
        "runtime" : 301480,
        "total_ios" : 20077,
        "short_ios" : 0,
        "drop_ios" : 0,
        "slat_ns" : {
          "min" : 74901,
          "max" : 1927142,
          "mean" : 121206.238432,
          "stddev" : 54277.298348,
          "N" : 20077
        },
        "clat_ns" : {
          "min" : 850805444,
          "max" : 129662400521,
          "mean" : 30609931045.147789,
          "stddev" : 30334446289.206055,
          "N" : 20077,
          "percentile" : {
            "1.000000" : 2466250752,
            "5.000000" : 3103784960,
            "10.000000" : 3338665984,
            "20.000000" : 3607101440,
            "30.000000" : 4076863488,
            "40.000000" : 17112760320,
            "50.000000" : 17112760320,
            "60.000000" : 17112760320,
            "70.000000" : 17112760320,
            "80.000000" : 17112760320,
            "90.000000" : 17112760320,
            "95.000000" : 17112760320,
            "99.000000" : 17112760320,
            "99.500000" : 17112760320,
            "99.900000" : 17112760320,
            "99.950000" : 17112760320,
            "99.990000" : 17112760320
          }
        },
        "lat_ns" : {
          "min" : 851003096,
          "max" : 129662481742,
          "mean" : 30610053467.462868,
          "stddev" : 30334446617.088341,
          "N" : 20077
        },
        "bw_min" : 128,
        "bw_max" : 3520,
        "bw_agg" : 100.000000,
        "bw_mean" : 614.110630,
        "bw_dev" : 42.261512,
        "bw_samples" : 3768,
        "iops_min" : 32,
        "iops_max" : 880,
        "iops_mean" : 153.527657,
        "iops_stddev" : 10.565378,
        "iops_samples" : 3768
      },
      "trim" : {
        "io_bytes" : 0,
        "io_kbytes" : 0,
        "bw_bytes" : 0,
        "bw" : 0,
        "iops" : 0.000000,
        "runtime" : 0,
        "total_ios" : 0,
        "short_ios" : 0,
        "drop_ios" : 0,
        "slat_ns" : {
          "min" : 0,
          "max" : 0,
          "mean" : 0.000000,
          "stddev" : 0.000000,
          "N" : 0
        },
        "clat_ns" : {
          "min" : 0,
          "max" : 0,
          "mean" : 0.000000,
          "stddev" : 0.000000,
          "N" : 0
        },
        "lat_ns" : {
          "min" : 0,
          "max" : 0,
          "mean" : 0.000000,
          "stddev" : 0.000000,
          "N" : 0
        },
        "bw_min" : 0,
        "bw_max" : 0,
        "bw_agg" : 0.000000,
        "bw_mean" : 0.000000,
        "bw_dev" : 0.000000,
        "bw_samples" : 0,
        "iops_min" : 0,
        "iops_max" : 0,
        "iops_mean" : 0.000000,
        "iops_stddev" : 0.000000,
        "iops_samples" : 0
      },
      "sync" : {
        "total_ios" : 0,
        "lat_ns" : {
          "min" : 0,
          "max" : 0,
          "mean" : 0.000000,
          "stddev" : 0.000000,
          "N" : 0
        }
      },
      "job_runtime" : 4807739,
      "usr_cpu" : 0.017950,
      "sys_cpu" : 0.122303,
      "ctx" : 20128,
      "majf" : 0,
      "minf" : 656,
      "iodepth_level" : {
        "1" : 0.100000,
        "2" : 0.100000,
        "4" : 0.159705,
        "8" : 0.319409,
        "16" : 0.638818,
        "32" : 1.277636,
        ">=64" : 97.484653
      },
      "iodepth_submit" : {
        "0" : 0.000000,
        "4" : 100.000000,
        "8" : 0.000000,
        "16" : 0.000000,
        "32" : 0.000000,
        "64" : 0.000000,
        ">=64" : 0.000000
      },
      "iodepth_complete" : {
        "0" : 0.000000,
        "4" : 99.955568,
        "8" : 0.000000,
        "16" : 0.000000,
        "32" : 0.000000,
        "64" : 0.000000,
        ">=64" : 0.100000
      },
      "latency_ns" : {
        "2" : 0.000000,
        "4" : 0.000000,
        "10" : 0.000000,
        "20" : 0.000000,
        "50" : 0.000000,
        "100" : 0.000000,
        "250" : 0.000000,
        "500" : 0.000000,
        "750" : 0.000000,
        "1000" : 0.000000
      },
      "latency_us" : {
        "2" : 0.000000,
        "4" : 0.000000,
        "10" : 0.000000,
        "20" : 0.000000,
        "50" : 0.039926,
        "100" : 0.000000,
        "250" : 0.000000,
        "500" : 0.000000,
        "750" : 0.000000,
        "1000" : 0.000000
      },
      "latency_ms" : {
        "2" : 0.000000,
        "4" : 0.000000,
        "10" : 0.000000,
        "20" : 0.000000,
        "50" : 0.000000,
        "100" : 0.000000,
        "250" : 0.000000,
        "500" : 0.000000,
        "750" : 0.000000,
        "1000" : 0.044917,
        "2000" : 0.239557,
        ">=2000" : 99.675600
      },
      "latency_depth" : 256,
      "latency_target" : 0,
      "latency_percentile" : 100.000000,
      "latency_window" : 0
    }
  ]
}
