{
  "fio version" : "fio-3.27",
  "timestamp" : 1627029448,
  "timestamp_ms" : 1627029448743,
  "time" : "Fri Jul 23 10:37:28 2021",
  "jobs" : [
    {
      "jobname" : "randrw",
      "groupid" : 0,
      "error" : 0,
      "eta" : 0,
      "elapsed" : 301,
      "job options" : {
        "bs" : "4K",
        "iodepth" : "256",
        "direct" : "0",
        "ioengine" : "libaio",
        "time_based" : "1",
        "runtime" : "300",
        "numjobs" : "4",
        "size" : "1g",
        "name" : "randrw",
        "rw" : "randrw",
        "directory" : "/scratch/snx2000/ccocha/randrw/150_node",
        "filename_format" : "$jobname.43.$jobnum.$filenum"
      },
      "read" : {
        "io_bytes" : 78241792,
        "io_kbytes" : 76408,
        "bw_bytes" : 260693,
        "bw" : 254,
        "iops" : 63.645754,
        "runtime" : 300130,
        "total_ios" : 19102,
        "short_ios" : 0,
        "drop_ios" : 0,
        "slat_ns" : {
          "min" : 469066,
          "max" : 33350532351,
          "mean" : 62683422.773060,
          "stddev" : 450498875.554098,
          "N" : 19102
        },
        "clat_ns" : {
          "min" : 18940,
          "max" : 53381296847,
          "mean" : 7854893384.379797,
          "stddev" : 7319286865.948907,
          "N" : 19102,
          "percentile" : {
            "1.000000" : 918552576,
            "5.000000" : 1027604480,
            "10.000000" : 1098907648,
            "20.000000" : 1350565888,
            "30.000000" : 6744440832,
            "40.000000" : 7415529472,
            "50.000000" : 7818182656,
            "60.000000" : 8287944704,
            "70.000000" : 8791261184,
            "80.000000" : 9328132096,
            "90.000000" : 10267656192,
            "95.000000" : 11207180288,
            "99.000000" : 17112760320,
            "99.500000" : 17112760320,
            "99.900000" : 17112760320,
            "99.950000" : 17112760320,
            "99.990000" : 17112760320
          }
        },
        "lat_ns" : {
          "min" : 4799758,
          "max" : 53916464987,
          "mean" : 7917579707.674067,
          "stddev" : 7348719102.826653,
          "N" : 19102
        },
        "bw_min" : 32,
        "bw_max" : 2432,
        "bw_agg" : 100.000000,
        "bw_mean" : 315.544322,
        "bw_dev" : 87.676717,
        "bw_samples" : 1879,
        "iops_min" : 8,
        "iops_max" : 608,
        "iops_mean" : 78.886080,
        "iops_stddev" : 21.919179,
        "iops_samples" : 1879
      },
      "write" : {
        "io_bytes" : 80134144,
        "io_kbytes" : 78256,
        "bw_bytes" : 266998,
        "bw" : 260,
        "iops" : 65.185086,
        "runtime" : 300130,
        "total_ios" : 19564,
        "short_ios" : 0,
        "drop_ios" : 0,
        "slat_ns" : {
          "min" : 75711,
          "max" : 2104425,
          "mean" : 113079.505469,
          "stddev" : 45052.687744,
          "N" : 19564
        },
        "clat_ns" : {
          "min" : 11970,
          "max" : 53010838523,
          "mean" : 7949484209.258896,
          "stddev" : 7583052461.129703,
          "N" : 19564,
          "percentile" : {
            "1.000000" : 918552576,
            "5.000000" : 1035993088,
            "10.000000" : 1098907648,
            "20.000000" : 1300234240,
            "30.000000" : 6811549696,
            "40.000000" : 7415529472,
            "50.000000" : 7885291520,
            "60.000000" : 8287944704,
            "70.000000" : 8791261184,
            "80.000000" : 9328132096,
            "90.000000" : 10401873920,
            "95.000000" : 11207180288,
            "99.000000" : 17112760320,
            "99.500000" : 17112760320,
            "99.900000" : 17112760320,
            "99.950000" : 17112760320,
            "99.990000" : 17112760320
          }
        },
        "lat_ns" : {
          "min" : 95961,
          "max" : 53010918194,
          "mean" : 7949598455.388564,
          "stddev" : 7583052840.619589,
          "N" : 19564
        },
        "bw_min" : 32,
        "bw_max" : 2496,
        "bw_agg" : 100.000000,
        "bw_mean" : 323.392384,
        "bw_dev" : 90.822310,
        "bw_samples" : 1884,
        "iops_min" : 8,
        "iops_max" : 624,
        "iops_mean" : 80.848096,
        "iops_stddev" : 22.705578,
        "iops_samples" : 1884
      },
      "trim" : {
        "io_bytes" : 0,
        "io_kbytes" : 0,
        "bw_bytes" : 0,
        "bw" : 0,
        "iops" : 0.000000,
        "runtime" : 0,
        "total_ios" : 0,
        "short_ios" : 0,
        "drop_ios" : 0,
        "slat_ns" : {
          "min" : 0,
          "max" : 0,
          "mean" : 0.000000,
          "stddev" : 0.000000,
          "N" : 0
        },
        "clat_ns" : {
          "min" : 0,
          "max" : 0,
          "mean" : 0.000000,
          "stddev" : 0.000000,
          "N" : 0
        },
        "lat_ns" : {
          "min" : 0,
          "max" : 0,
          "mean" : 0.000000,
          "stddev" : 0.000000,
          "N" : 0
        },
        "bw_min" : 0,
        "bw_max" : 0,
        "bw_agg" : 0.000000,
        "bw_mean" : 0.000000,
        "bw_dev" : 0.000000,
        "bw_samples" : 0,
        "iops_min" : 0,
        "iops_max" : 0,
        "iops_mean" : 0.000000,
        "iops_stddev" : 0.000000,
        "iops_samples" : 0
      },
      "sync" : {
        "total_ios" : 0,
        "lat_ns" : {
          "min" : 0,
          "max" : 0,
          "mean" : 0.000000,
          "stddev" : 0.000000,
          "N" : 0
        }
      },
      "job_runtime" : 1200273,
      "usr_cpu" : 0.062569,
      "sys_cpu" : 0.435734,
      "ctx" : 19134,
      "majf" : 0,
      "minf" : 174,
      "iodepth_level" : {
        "1" : 0.100000,
        "2" : 0.100000,
        "4" : 0.100000,
        "8" : 0.100000,
        "16" : 0.165520,
        "32" : 0.331040,
        ">=64" : 99.348265
      },
      "iodepth_submit" : {
        "0" : 0.000000,
        "4" : 100.000000,
        "8" : 0.000000,
        "16" : 0.000000,
        "32" : 0.000000,
        "64" : 0.000000,
        ">=64" : 0.000000
      },
      "iodepth_complete" : {
        "0" : 0.000000,
        "4" : 99.989376,
        "8" : 0.000000,
        "16" : 0.000000,
        "32" : 0.000000,
        "64" : 0.000000,
        ">=64" : 0.100000
      },
      "latency_ns" : {
        "2" : 0.000000,
        "4" : 0.000000,
        "10" : 0.000000,
        "20" : 0.000000,
        "50" : 0.000000,
        "100" : 0.000000,
        "250" : 0.000000,
        "500" : 0.000000,
        "750" : 0.000000,
        "1000" : 0.000000
      },
      "latency_us" : {
        "2" : 0.000000,
        "4" : 0.000000,
        "10" : 0.000000,
        "20" : 0.010000,
        "50" : 0.010000,
        "100" : 0.000000,
        "250" : 0.010000,
        "500" : 0.000000,
        "750" : 0.000000,
        "1000" : 0.000000
      },
      "latency_ms" : {
        "2" : 0.000000,
        "4" : 0.000000,
        "10" : 0.010000,
        "20" : 0.010000,
        "50" : 0.010000,
        "100" : 0.020690,
        "250" : 0.085346,
        "500" : 0.134485,
        "750" : 0.113795,
        "1000" : 2.415559,
        "2000" : 17.777893,
        ">=2000" : 79.426369
      },
      "latency_depth" : 256,
      "latency_target" : 0,
      "latency_percentile" : 100.000000,
      "latency_window" : 0
    }
  ]
}
