{
  "fio version" : "fio-3.27",
  "timestamp" : 1627021526,
  "timestamp_ms" : 1627021526181,
  "time" : "Fri Jul 23 08:25:26 2021",
  "jobs" : [
    {
      "jobname" : "randrw",
      "groupid" : 0,
      "error" : 0,
      "eta" : 0,
      "elapsed" : 301,
      "job options" : {
        "bs" : "4K",
        "iodepth" : "256",
        "direct" : "0",
        "ioengine" : "libaio",
        "time_based" : "1",
        "runtime" : "300",
        "numjobs" : "1",
        "size" : "1g",
        "name" : "randrw",
        "rw" : "randrw",
        "directory" : "/scratch/snx2000/ccocha/randrw/96_node",
        "filename_format" : "$jobname.94.$jobnum.$filenum"
      },
      "read" : {
        "io_bytes" : 97837056,
        "io_kbytes" : 95544,
        "bw_bytes" : 326089,
        "bw" : 318,
        "iops" : 79.611773,
        "runtime" : 300031,
        "total_ios" : 23886,
        "short_ios" : 0,
        "drop_ios" : 0,
        "slat_ns" : {
          "min" : 485193,
          "max" : 870433709,
          "mean" : 12427492.957171,
          "stddev" : 29008882.298053,
          "N" : 23886
        },
        "clat_ns" : {
          "min" : 12390,
          "max" : 9906373332,
          "mean" : 1601706075.276856,
          "stddev" : 846830589.912011,
          "N" : 23886,
          "percentile" : {
            "1.000000" : 608174080,
            "5.000000" : 683671552,
            "10.000000" : 742391808,
            "20.000000" : 985661440,
            "30.000000" : 1249902592,
            "40.000000" : 1384120320,
            "50.000000" : 1518338048,
            "60.000000" : 1652555776,
            "70.000000" : 1786773504,
            "80.000000" : 1988100096,
            "90.000000" : 2365587456,
            "95.000000" : 2801795072,
            "99.000000" : 4462739456,
            "99.500000" : 6140461056,
            "99.900000" : 9865003008,
            "99.950000" : 9865003008,
            "99.990000" : 9865003008
          }
        },
        "lat_ns" : {
          "min" : 50121620,
          "max" : 9908142773,
          "mean" : 1614135969.445404,
          "stddev" : 850081512.924205,
          "N" : 23886
        },
        "bw_min" : 8,
        "bw_max" : 912,
        "bw_agg" : 100.000000,
        "bw_mean" : 320.733108,
        "bw_dev" : 198.388516,
        "bw_samples" : 592,
        "iops_min" : 2,
        "iops_max" : 228,
        "iops_mean" : 80.182432,
        "iops_stddev" : 49.595936,
        "iops_samples" : 592
      },
      "write" : {
        "io_bytes" : 97402880,
        "io_kbytes" : 95120,
        "bw_bytes" : 324642,
        "bw" : 317,
        "iops" : 79.258477,
        "runtime" : 300031,
        "total_ios" : 23780,
        "short_ios" : 0,
        "drop_ios" : 0,
        "slat_ns" : {
          "min" : 75551,
          "max" : 940136,
          "mean" : 102776.702313,
          "stddev" : 38983.908303,
          "N" : 23780
        },
        "clat_ns" : {
          "min" : 52452314,
          "max" : 9908021862,
          "mean" : 1604088983.215011,
          "stddev" : 852943278.322710,
          "N" : 23780,
          "percentile" : {
            "1.000000" : 616562688,
            "5.000000" : 683671552,
            "10.000000" : 742391808,
            "20.000000" : 985661440,
            "30.000000" : 1249902592,
            "40.000000" : 1384120320,
            "50.000000" : 1518338048,
            "60.000000" : 1652555776,
            "70.000000" : 1786773504,
            "80.000000" : 1988100096,
            "90.000000" : 2365587456,
            "95.000000" : 2801795072,
            "99.000000" : 4529848320,
            "99.500000" : 6140461056,
            "99.900000" : 9865003008,
            "99.950000" : 9865003008,
            "99.990000" : 9865003008
          }
        },
        "lat_ns" : {
          "min" : 52530274,
          "max" : 9908106412,
          "mean" : 1604192906.289361,
          "stddev" : 852944194.428894,
          "N" : 23780
        },
        "bw_min" : 8,
        "bw_max" : 928,
        "bw_agg" : 100.000000,
        "bw_mean" : 321.409864,
        "bw_dev" : 197.582615,
        "bw_samples" : 588,
        "iops_min" : 2,
        "iops_max" : 232,
        "iops_mean" : 80.350340,
        "iops_stddev" : 49.392973,
        "iops_samples" : 588
      },
      "trim" : {
        "io_bytes" : 0,
        "io_kbytes" : 0,
        "bw_bytes" : 0,
        "bw" : 0,
        "iops" : 0.000000,
        "runtime" : 0,
        "total_ios" : 0,
        "short_ios" : 0,
        "drop_ios" : 0,
        "slat_ns" : {
          "min" : 0,
          "max" : 0,
          "mean" : 0.000000,
          "stddev" : 0.000000,
          "N" : 0
        },
        "clat_ns" : {
          "min" : 0,
          "max" : 0,
          "mean" : 0.000000,
          "stddev" : 0.000000,
          "N" : 0
        },
        "lat_ns" : {
          "min" : 0,
          "max" : 0,
          "mean" : 0.000000,
          "stddev" : 0.000000,
          "N" : 0
        },
        "bw_min" : 0,
        "bw_max" : 0,
        "bw_agg" : 0.000000,
        "bw_mean" : 0.000000,
        "bw_dev" : 0.000000,
        "bw_samples" : 0,
        "iops_min" : 0,
        "iops_max" : 0,
        "iops_mean" : 0.000000,
        "iops_stddev" : 0.000000,
        "iops_samples" : 0
      },
      "sync" : {
        "total_ios" : 0,
        "lat_ns" : {
          "min" : 0,
          "max" : 0,
          "mean" : 0.000000,
          "stddev" : 0.000000,
          "N" : 0
        }
      },
      "job_runtime" : 300030,
      "usr_cpu" : 0.280639,
      "sys_cpu" : 1.910142,
      "ctx" : 23896,
      "majf" : 0,
      "minf" : 41,
      "iodepth_level" : {
        "1" : 0.100000,
        "2" : 0.100000,
        "4" : 0.100000,
        "8" : 0.100000,
        "16" : 0.100000,
        "32" : 0.100000,
        ">=64" : 99.867830
      },
      "iodepth_submit" : {
        "0" : 0.000000,
        "4" : 100.000000,
        "8" : 0.000000,
        "16" : 0.000000,
        "32" : 0.000000,
        "64" : 0.000000,
        ">=64" : 0.000000
      },
      "iodepth_complete" : {
        "0" : 0.000000,
        "4" : 99.997891,
        "8" : 0.000000,
        "16" : 0.000000,
        "32" : 0.000000,
        "64" : 0.000000,
        ">=64" : 0.100000
      },
      "latency_ns" : {
        "2" : 0.000000,
        "4" : 0.000000,
        "10" : 0.000000,
        "20" : 0.000000,
        "50" : 0.000000,
        "100" : 0.000000,
        "250" : 0.000000,
        "500" : 0.000000,
        "750" : 0.000000,
        "1000" : 0.000000
      },
      "latency_us" : {
        "2" : 0.000000,
        "4" : 0.000000,
        "10" : 0.000000,
        "20" : 0.010000,
        "50" : 0.000000,
        "100" : 0.000000,
        "250" : 0.000000,
        "500" : 0.000000,
        "750" : 0.000000,
        "1000" : 0.000000
      },
      "latency_ms" : {
        "2" : 0.000000,
        "4" : 0.000000,
        "10" : 0.000000,
        "20" : 0.000000,
        "50" : 0.000000,
        "100" : 0.046154,
        "250" : 0.046154,
        "500" : 0.037763,
        "750" : 10.516930,
        "1000" : 9.702933,
        "2000" : 60.514832,
        ">=2000" : 19.133135
      },
      "latency_depth" : 256,
      "latency_target" : 0,
      "latency_percentile" : 100.000000,
      "latency_window" : 0
    }
  ]
}
